cfnyaml/__init__.py
cfnyaml/funcbase.py
cfnyaml/funcs.py
cfn_yaml-0.1.3.dist-info/METADATA
cfn_yaml-0.1.3.dist-info/WHEEL
cfn_yaml-0.1.3.dist-info/top_level.txt
cfn_yaml-0.1.3.dist-info/RECORD
