Metadata-Version: 2.1
Name: cfn-yaml
Version: 0.1.3
Summary: Let you load cloudformation template.yaml
Home-page: https://github.com/Just4test/cfn-yaml
Author: Just4test
Author-email: myservice@just4test.net
License: wtfpl
Keywords: CloudFormation,YAML
Platform: any
Classifier: Development Status :: 3 - Alpha
Classifier: Programming Language :: Python :: 3 :: Only
Requires-Dist: ruamel.yaml
